chaplin/optimize.py
chaplin/predict.py
chaplin/marshalled/final_modelFinalLayer.stateDict
chaplin/marshalled/probability_scaler.m
chaplin/marshalled/final_modelBert.hugg_m/config.json
chaplin/marshalled/final_modelBert.hugg_m/pytorch_model.bin
chaplin/src/NNWrappers.py
chaplin/src/geneticOptim.py
chaplin/src/model.py
chaplin/src/parse.py
chaplin/src/predict.py
chaplin/src/utils.py
chaplin-0.0.3.data/scripts/chaplin_standalone
chaplin-0.0.3.dist-info/licenses/LICENSE
chaplin-0.0.3.dist-info/METADATA
chaplin-0.0.3.dist-info/WHEEL
chaplin-0.0.3.dist-info/top_level.txt
chaplin-0.0.3.dist-info/RECORD
