Metadata-Version: 2.4
Name: chaplin
Version: 0.0.3
Summary: A predictor of protein-chaperon interaction
Home-page: https://github.com/grogdrinker/chaplin
Author: Gabriele Orlando
Author-email: gabriele.orlando@kuleuven.be
Classifier: Programming Language :: Python :: 3
Classifier: Operating System :: OS Independent
License-File: LICENSE
Requires-Dist: torch
Requires-Dist: numpy
Requires-Dist: scikit-learn
Requires-Dist: transformers
Dynamic: author
Dynamic: author-email
Dynamic: classifier
Dynamic: description
Dynamic: description-content-type
Dynamic: home-page
Dynamic: license-file
Dynamic: requires-dist
Dynamic: summary
